llcv/__init__.py
llcv-0.0.5.dist-info/LICENSE
llcv-0.0.5.dist-info/METADATA
llcv-0.0.5.dist-info/WHEEL
llcv-0.0.5.dist-info/top_level.txt
llcv-0.0.5.dist-info/RECORD
